[
    {
        "shipping_line": "NYK",
        "vessel_voyage": "ALTAIR LEADER 104",
        "type": "RO-RO",
        "departures": [
            {
                "date": "2026/05/21",
                "port": "YOKOHAMA"
            },
            {
                "date": "2026/05/23",
                "port": "NAGOYA"
            },
            {
                "date": "2026/05/25",
                "port": "OSAKA"
            }
        ],
        "arrival": {
            "date": "2026/06/05",
            "port": "Hambantota"
        }
    },
    {
        "shipping_line": "SEVEN SEALS CO.,LTD",
        "vessel_voyage": "TURANDOT 704",
        "type": "RO-RO",
        "departures": [
            {
                "date": "2026/05/27",
                "port": "HITACHINAKA"
            },
            {
                "date": "2026/05/28",
                "port": "YOKOHAMA"
            },
            {
                "date": "2026/05/29",
                "port": "NAGOYA"
            },
            {
                "date": "2026/05/30",
                "port": "OSAKA"
            }
        ],
        "arrival": {
            "date": "2026/06/11",
            "port": "Hambantota"
        }
    },
    {
        "shipping_line": "SEVEN SEALS CO.,LTD",
        "vessel_voyage": "VIKING DRIVE 40",
        "type": "RO-RO",
        "departures": [
            {
                "date": "2026/06/08",
                "port": "YOKOHAMA"
            },
            {
                "date": "2026/06/10",
                "port": "NAGOYA"
            },
            {
                "date": "2026/06/11",
                "port": "OSAKA"
            }
        ],
        "arrival": {
            "date": "2026/06/22",
            "port": "Hambantota"
        }
    },
    {
        "shipping_line": "NYK",
        "vessel_voyage": "GENTLE LEADER 121",
        "type": "RO-RO",
        "departures": [
            {
                "date": "2026/06/18",
                "port": "NAGOYA"
            },
            {
                "date": "2026/06/19",
                "port": "KOBE"
            },
            {
                "date": "2026/06/21",
                "port": "YOKOHAMA"
            }
        ],
        "arrival": {
            "date": "2026/07/02",
            "port": "Hambantota"
        }
    },
    {
        "shipping_line": "NYK",
        "vessel_voyage": "OPAL LEADER 053",
        "type": "RO-RO",
        "departures": [
            {
                "date": "2026/06/16",
                "port": "YOKOHAMA"
            },
            {
                "date": "2026/06/17",
                "port": "NAGOYA"
            },
            {
                "date": "2026/06/18",
                "port": "OSAKA"
            }
        ],
        "arrival": {
            "date": "2026/07/04",
            "port": "Hambantota"
        }
    },
    {
        "shipping_line": "NYK",
        "vessel_voyage": "VENUS LEADER 082",
        "type": "RO-RO",
        "departures": [
            {
                "date": "2026/06/22",
                "port": "YOKOHAMA"
            },
            {
                "date": "2026/06/23",
                "port": "NAGOYA"
            },
            {
                "date": "2026/06/25",
                "port": "OSAKA"
            },
            {
                "date": "2026/06/26",
                "port": "KOBE"
            }
        ],
        "arrival": {
            "date": "2026/07/07",
            "port": "Hambantota"
        }
    },
    {
        "shipping_line": "NYK",
        "vessel_voyage": "STRAITS CHALLENGER 351",
        "type": "RO-RO",
        "departures": [
            {
                "date": "2026/06/25",
                "port": "YOKOHAMA"
            },
            {
                "date": "2026/06/26",
                "port": "KAWASAKI"
            },
            {
                "date": "2026/06/29",
                "port": "OSAKA"
            },
            {
                "date": "2026/07/01",
                "port": "KOBE"
            },
            {
                "date": "2026/07/02",
                "port": "NAGOYA"
            }
        ],
        "arrival": {
            "date": "2026/07/12",
            "port": "Hambantota"
        }
    },
    {
        "shipping_line": "SEVEN SEALS CO.,LTD",
        "vessel_voyage": "DON JUAN 706",
        "type": "RO-RO",
        "departures": [
            {
                "date": "2026/06/17",
                "port": "HITACHINAKA"
            },
            {
                "date": "2026/06/18",
                "port": "YOKOHAMA"
            },
            {
                "date": "2026/06/20",
                "port": "NAGOYA"
            },
            {
                "date": "2026/06/21",
                "port": "OSAKA"
            }
        ],
        "arrival": {
            "date": "2026/07/16",
            "port": "Hambantota"
        }
    },
    {
        "shipping_line": "G ALLIANCE SHIPPING",
        "vessel_voyage": "G POSEIDON 078",
        "type": "RO-RO",
        "departures": [
            {
                "date": "2026/06/22",
                "port": "YOKOHAMA"
            }
        ],
        "arrival": {
            "date": "2026/07/22",
            "port": "Hambantota"
        }
    },
    {
        "shipping_line": "G ALLIANCE SHIPPING",
        "vessel_voyage": "GLOVIS SIRIUS 070",
        "type": "RO-RO",
        "departures": [
            {
                "date": "2026/07/10",
                "port": "HAKATA"
            },
            {
                "date": "2026/07/12",
                "port": "OSAKA"
            },
            {
                "date": "2026/07/13",
                "port": "KISARAZU"
            }
        ],
        "arrival": {
            "date": "2026/07/28",
            "port": "Hambantota"
        }
    },
    {
        "shipping_line": "NYK",
        "vessel_voyage": "HARMONY LEADER 104",
        "type": "RO-RO",
        "departures": [
            {
                "date": "2026/07/13",
                "port": "YOKOHAMA"
            },
            {
                "date": "2026/07/14",
                "port": "NAGOYA"
            },
            {
                "date": "2026/07/16",
                "port": "OSAKA"
            },
            {
                "date": "2026/07/17",
                "port": "KOBE"
            }
        ],
        "arrival": {
            "date": "2026/07/30",
            "port": "Hambantota"
        }
    },
    {
        "shipping_line": "SEVEN SEALS CO.,LTD",
        "vessel_voyage": "VIKING DRIVE 41",
        "type": "RO-RO",
        "departures": [
            {
                "date": "2026/07/20",
                "port": "OSAKA"
            },
            {
                "date": "2026/07/21",
                "port": "NAGOYA"
            },
            {
                "date": "2026/07/22",
                "port": "YOKOHAMA"
            }
        ],
        "arrival": {
            "date": "2026/08/07",
            "port": "Hambantota"
        }
    }
]